github_rest_cli/__init__.py
github_rest_cli/api.py
github_rest_cli/config.py
github_rest_cli/globals.py
github_rest_cli/main.py
github_rest_cli/utils.py
github_rest_cli-1.0.3.dist-info/METADATA
github_rest_cli-1.0.3.dist-info/WHEEL
github_rest_cli-1.0.3.dist-info/entry_points.txt
github_rest_cli-1.0.3.dist-info/licenses/LICENSE
github_rest_cli-1.0.3.dist-info/RECORD
