Metadata-Version: 2.4
Name: github-rest-cli
Version: 1.0.3
Summary: GitHub REST API cli
Author-email: lbrealdev <lbrealdeveloper@gmail.com>
License-File: LICENSE
Requires-Python: >=3.11.5
Requires-Dist: dynaconf>=3.2.11
Requires-Dist: requests>=2.31.0
Requires-Dist: rich>=14.0.0
